__init__.py
src/AbstractTextObfuscationDPMechanism.py
src/__init__.py
src/EmbeddingPerturbationMechanism/AbstractEmbeddingPerturbationMechanism.py
src/EmbeddingPerturbationMechanism/__init__.py
src/EmbeddingPerturbationMechanism/cmp.py
src/EmbeddingPerturbationMechanism/mahalanobis.py
src/EmbeddingPerturbationMechanism/vickrey.py
src/SamplingPerturbationMechanism/AbstractSamplingPerturbationMechanism.py
src/SamplingPerturbationMechanism/__init__.py
src/SamplingPerturbationMechanism/custext.py
src/SamplingPerturbationMechanism/santext.py
src/SamplingPerturbationMechanism/tem.py
src/utils/__init__.py
src/utils/helper.py
src/utils/metrics.py
src/utils/vocab.py
pypantera-1.0.2.dist-info/LICENSE
pypantera-1.0.2.dist-info/METADATA
pypantera-1.0.2.dist-info/WHEEL
pypantera-1.0.2.dist-info/top_level.txt
pypantera-1.0.2.dist-info/RECORD
