Metadata-Version: 2.1
Name: pypantera
Version: 1.0.2
Summary: A Python Package for NLP Obfuscation using Differential Privacy
Home-page: https://github.com/Kekkodf/pypantera
Author: Francesco L. De Faveri
Author-email: francescoluigi.defaveri@phd.unipd.it
Project-URL: Bug Reports, https://github.com/Kekkodf/pypantera/issues
Project-URL: Source, https://github.com/Kekkodf/pypantera
Keywords: Differential Privacy,NLP,Obfuscation,Anonymization
Classifier: Development Status :: 4 - Beta
Classifier: Operating System :: OS Independent
Classifier: Programming Language :: Python :: 3
Classifier: Programming Language :: Python :: 3.7
Classifier: Programming Language :: Python :: 3.8
Classifier: Programming Language :: Python :: 3.9
Classifier: Programming Language :: Python :: 3.10
Classifier: Programming Language :: Python :: 3.11
Classifier: Programming Language :: Python :: 3.12
Classifier: Programming Language :: Python :: 3 :: Only
Requires-Python: >=3.7
License-File: LICENSE
Requires-Dist: gensim
Requires-Dist: multiprocess
Requires-Dist: nltk
Requires-Dist: numpy
Requires-Dist: pandas
Requires-Dist: pip
Requires-Dist: scikit-learn
Requires-Dist: scipy
Requires-Dist: tqdm
